{"istat":{"hostname":"apex","software":"5.12_CA25","hardware":"1.0","serial":"AC5:59653","type":"AC5","extra":{"sdver":"SS16G,3,5344,2,0","sddate": "180901","sdserial": 3359085936,"sdextDate": "","sdhealth": 0,"WWWVer": "PASS","TmpUart": "PASS","pH2Uart": "PASS","CondUart": "PASS","sdstat": {"reads":669790158,"writes":338178,"readErr":0,"writeErr":0 }},"timezone":"-7.00","date":1775758000,
"feed":{"name":0,"active":0}
,
"power":{"failed":1766660046,"restored":0}
,
"inputs":[{"did":"base_Temp","type":"Temp","name":"Temp","value":78.6 }
,{"did":"base_pH","type":"pH","name":"pH","value":8.23 }
,{"did":"base_ORP","type":"ORP","name":"ORP","value":324  }
,{"did":"base_Cond","type":"Cond","name":"Salt","value":31.9 }
,{"did":"2_P0","type":"Amps","name":"Alk","value":0.0  }
,{"did":"2_P1","type":"Amps","name":"Ca","value":0.0  }
,{"did":"2_P2","type":"Amps","name":"Mg","value":0.0  }
,{"did":"2_P3","type":"Amps","name":"RO_BoosterA","value":0.0  }
,{"did":"2_P4","type":"Amps","name":"OzoneA","value":0.0  }
,{"did":"2_P5","type":"Amps","name":"Pump_2_6A","value":0.0  }
,{"did":"2_P6","type":"Amps","name":"RefLght_2_7A","value":0.0  }
,{"did":"2_P7","type":"Amps","name":"GPower8A","value":0.0  }
,{"did":"2_P8","type":"pwr","name":"PowerStripW","value":  10 }
,{"did":"2_P9","type":"pwr","name":"NSW_HeaterW","value":   0 }
,{"did":"2_P10","type":"pwr","name":"NSW_PumpW","value":   1 }
,{"did":"2_P11","type":"pwr","name":"RO_BoosterW","value":   0 }
,{"did":"2_P12","type":"pwr","name":"OzoneW","value":   5 }
,{"did":"2_P13","type":"pwr","name":"Pump_2_6W","value":   1 }
,{"did":"2_P14","type":"pwr","name":"RefLght_2_7W","value":   0 }
,{"did":"2_P15","type":"pwr","name":"GPower8W","value":   1 }
,{"did":"2_P16","type":"volts","name":"Volt_2","value":120  }
,{"did":"4_P0","type":"Amps","name":"WaveEngineA","value":0.0  }
,{"did":"4_P1","type":"Amps","name":"Bottom2A","value":0.0  }
,{"did":"4_P2","type":"Amps","name":"RetPump_4_3A","value":0.0  }
,{"did":"4_P3","type":"Amps","name":"Heater_4_4A","value":0.0  }
,{"did":"4_P4","type":"Amps","name":"Skimmer_4_5A","value":0.0  }
,{"did":"4_P5","type":"Amps","name":"Pump_4_6A","value":0.0  }
,{"did":"4_P6","type":"Amps","name":"AxisA","value":0.2  }
,{"did":"4_P7","type":"Amps","name":"SkimmerA","value":0.1  }
,{"did":"4_P8","type":"pwr","name":"WaveEngineW","value":   1 }
,{"did":"4_P9","type":"pwr","name":"Bottom2W","value":   1 }
,{"did":"4_P10","type":"pwr","name":"RetPump_4_3W","value":   1 }
,{"did":"4_P11","type":"pwr","name":"Heater_4_4W","value":   0 }
,{"did":"4_P12","type":"pwr","name":"Skimmer_4_5W","value":   1 }
,{"did":"4_P13","type":"pwr","name":"Pump_4_6W","value":   1 }
,{"did":"4_P14","type":"pwr","name":"AxisW","value":  17 }
,{"did":"4_P15","type":"pwr","name":"SkimmerW","value":  30 }
,{"did":"4_P16","type":"volts","name":"Volt_4","value":122  }
,{"did":"6_0","type":"po4","name":"PO4","value":0.03 }
,{"did":"6_1","type":"no3","name":"NO3","value":13.1 }
,{"did":"9_P0","type":"Amps","name":"InkbirdA","value":0.2  }
,{"did":"9_P1","type":"Amps","name":"ReactorA","value":0.0  }
,{"did":"9_P2","type":"Amps","name":"FanA","value":0.2  }
,{"did":"9_P3","type":"Amps","name":"Tunze_ATOA","value":0.0  }
,{"did":"9_P4","type":"Amps","name":"UVA","value":0.4  }
,{"did":"9_P5","type":"Amps","name":"ReefMatA","value":0.0  }
,{"did":"9_P6","type":"Amps","name":"Sump_FlowA","value":0.0  }
,{"did":"9_P7","type":"Amps","name":"Stand_LightA","value":0.0  }
,{"did":"9_P8","type":"pwr","name":"InkbirdW","value":   3 }
,{"did":"9_P9","type":"pwr","name":"ReactorW","value":   1 }
,{"did":"9_P10","type":"pwr","name":"FanW","value":  28 }
,{"did":"9_P11","type":"pwr","name":"Tunze_ATOW","value":   1 }
,{"did":"9_P12","type":"pwr","name":"UVW","value":  46 }
,{"did":"9_P13","type":"pwr","name":"ReefMatW","value":   3 }
,{"did":"9_P14","type":"pwr","name":"Sump_FlowW","value":   1 }
,{"did":"9_P15","type":"pwr","name":"Stand_LightW","value":  17 }
,{"did":"9_P16","type":"volts","name":"Volt_9","value":121  }
,{"did":"14_P1","type":"in","name":"RES_LV","value": 7.7 }
,{"did":"14_P2","type":"in","name":"ATO_LL","value": 3.7 }
,{"did":"18_0","type":"alk","name":"Alkx18","value":8.66 }
,{"did":"18_1","type":"ca","name":"Cax18","value": 464 }
,{"did":"18_2","type":"mg","name":"Mgx18","value":1325 }
,{"did":"19_1","type":"Cond","name":"Condx19","value": 1.2 }
,{"did":"21_P2","type":"in","name":"Rtn_lv","value": 8.3 }
,{"did":"22_P2","type":"in","name":"FRAG_R","value": 6.7 }
,{"did":"base_I1","name":"DoorSw","type":"digital","value":0},{"did":"base_I2","name":"Sw2","type":"digital","value":0},{"did":"base_I3","name":"Sw3","type":"digital","value":0},{"did":"base_I4","name":"Sw4","type":"digital","value":0},{"did":"base_I5","name":"Sw5","type":"digital","value":0},{"did":"base_I6","name":"SkimSW","type":"digital","value":0},{"did":"10_I1","name":"ATOLOW","type":"digital","value":200},{"did":"10_I2","name":"ATOMAX","type":"digital","value":0},{"did":"10_I3","name":"XLow","type":"digital","value":200},{"did":"10_I4","name":"Ext_Lo","type":"digital","value":200},{"did":"12_I1","name":"Alk_Lo","type":"digital","value":200},{"did":"12_I2","name":"CA_Low","type":"digital","value":0},{"did":"14_I1","name":"NSW_Hi","type":"digital","value":0},{"did":"14_I4","name":"NSW_Lo","type":"digital","value":200},{"did":"19_I1","name":"Master","type":"digital","value":0},{"did":"19_I2","name":"SWPump","type":"digital","value":0},{"did":"19_I3","name":"SWRODI","type":"digital","value":0},{"did":"19_I4","name":"Swx19_4","type":"digital","value":0},{"did":"19_I5","name":"Swx19_5","type":"digital","value":0},{"did":"19_I6","name":"Swx19_6","type":"digital","value":0},{"did":"21_I1","name":"Ret_Lo","type":"digital","value":200},{"did":"21_I2","name":"Ret_hi","type":"digital","value":0},{"did":"21_I4","name":"Swx21_4","type":"digital","value":200},{"did":"22_I1","name":"FRAG_L","type":"digital","value":200},{"did":"22_I2","name":"FRAG_H","type":"digital","value":0},{"did":"22_I4","name":"Swx22_4","type":"digital","value":0}],
"outputs":[{"status":["AON","","OK",""],"name":"WE-0to10","gid":"","type":"variable","ID":0,"did":"base_Var1"}
,{"status":["AOF","","OK",""],"name":"VarSpd2_I2","gid":"","type":"variable","ID":1,"did":"base_Var2"}
,{"status":["CorStandard","","OK",""],"name":"VarSpd3_I3","gid":"","type":"variable","ID":2,"did":"base_Var3"}
,{"status":["TBL","","OK",""],"name":"SkimmerPump","gid":"","type":"variable","ID":3,"did":"base_Var4"}
,{"status":["AOF","","OK",""],"name":"SndAlm_I6","gid":"","type":"alert","ID":4,"did":"base_Alarm"}
,{"status":["AOF","","OK",""],"name":"SndWrn_I7","gid":"","type":"alert","ID":5,"did":"base_Warn"}
,{"status":["AOF","","OK",""],"name":"Main_Alarm","gid":"","type":"alert","ID":6,"did":"base_email"}
,{"status":["AOF","","OK",""],"name":"Inkbird","gid":"","type":"outlet","ID":8,"did":"9_1"}
,{"status":["Pump_60_60","","OK",""],"name":"Reactor","gid":"","type":"outlet","ID":9,"did":"9_2"}
,{"status":["AON","","OK",""],"name":"Fan","gid":"","type":"outlet","ID":10,"did":"9_3"}
,{"status":["AON","","OK",""],"name":"Tunze_ATO","gid":"","type":"outlet","ID":11,"did":"9_4"}
,{"status":["AON","","OK",""],"name":"UV","gid":"","type":"outlet","ID":12,"did":"9_5"}
,{"status":["AON","","OK",""],"name":"ReefMat","gid":"","type":"outlet","ID":13,"did":"9_6"}
,{"status":["AON","","OK",""],"name":"Sump_Flow","gid":"","type":"outlet","ID":14,"did":"9_7"}
,{"status":["AON","","OK",""],"name":"Stand_Light","gid":"","type":"outlet","ID":15,"did":"9_8"}
,{"status":["OFF","","OK",""],"name":"top_dc24","gid":"","type":"24v","ID":16,"did":"9_9"}
,{"status":["OFF","","OK",""],"name":"LinkB_9_10","gid":"","type":"24v","ID":17,"did":"9_10"}
,{"status":["TBL","","OK","2000","0"],"name":"AWC_ADD","gid":"doserqd_3","type":"dqd","ID":18,"did":"3_1"}
,{"status":["TBL","50","OK","5026","2513","020","52"],"intensity":50,"name":"Return_Etc","gid":"","type":"cor|20","ID":19,"did":"11_1"}
,{"status":["OFF","","OK",""],"name":"WaveEngine","gid":"","type":"outlet","ID":20,"did":"4_1"}
,{"status":["AOF","","OK",""],"name":"Bottom2","gid":"","type":"outlet","ID":21,"did":"4_2"}
,{"status":["AON","","OK",""],"name":"RetPump_4_3","gid":"","type":"outlet","ID":22,"did":"4_3"}
,{"status":["AOF","","OK",""],"name":"Heater_4_4","gid":"","type":"outlet","ID":23,"did":"4_4"}
,{"status":["AON","","OK",""],"name":"Skimmer_4_5","gid":"","type":"outlet","ID":24,"did":"4_5"}
,{"status":["AON","","OK",""],"name":"Pump_4_6","gid":"","type":"outlet","ID":25,"did":"4_6"}
,{"status":["AON","","OK",""],"name":"Axis","gid":"","type":"outlet","ID":26,"did":"4_7"}
,{"status":["ON","","OK",""],"name":"Skimmer","gid":"","type":"outlet","ID":27,"did":"4_8"}
,{"status":["AOF","","OK",""],"name":"LinkA_4_9","gid":"","type":"24v","ID":28,"did":"4_9"}
,{"status":["OFF","","OK",""],"name":"LinkB_4_10","gid":"","type":"24v","ID":29,"did":"4_10"}
,{"status":["TBL","55","OK","4430","2215","104","59"],"intensity":55,"name":"Return_UV","gid":"","type":"cor|20","ID":30,"did":"5_1"}
,{"status":["TBL","","Asnc","OK"],"name":"Vortech3","gid":"0","type":"MXMPump|Ecotech|Vortech","ID":31,"did":"20_1"}
,{"status":["TBL","","RC","OK"],"name":"Vortech2","gid":"0","type":"MXMPump|Ecotech|Vortech","ID":32,"did":"20_2"}
,{"status":["TBL","","RC","OK"],"name":"Vortech1","gid":"0","type":"MXMPump|Ecotech|Vortech","ID":33,"did":"20_3"}
,{"status":["TBL","","Asnc","OK"],"name":"Vortech4","gid":"0","type":"MXMPump|Ecotech|Vortech","ID":34,"did":"20_4"}
,{"status":["AON","","OK",""],"name":"PowerStrip","gid":"","type":"outlet","ID":35,"did":"2_1"}
,{"status":["AOF","","OK",""],"name":"NSW_Heater","gid":"","type":"outlet","ID":36,"did":"2_2"}
,{"status":["AON","","OK",""],"name":"RunSkimmer","gid":"","type":"virtual","ID":37,"did":"Cntl_A1"}
,{"status":["AON","","OK",""],"name":"AllVortechs","gid":"","type":"virtual","ID":38,"did":"Cntl_A2"}
,{"status":["OFF","","OK",""],"name":"Feeder_Right","gid":"","type":"afs","ID":39,"did":"8_1"}
,{"status":["AOF","","OK","2000","721"],"name":"Alkalinity","gid":"doser_12","type":"dos","ID":40,"did":"12_1"}
,{"status":["TBL","","OK","2000","567"],"name":"Calcium","gid":"doser_12","type":"dos","ID":41,"did":"12_2"}
,{"status":["AOF","","OK",""],"name":"LinkA_13_1","gid":"","type":"24v","ID":42,"did":"13_1"}
,{"status":["AOF","","OK",""],"name":"LinkB_13_2","gid":"","type":"24v","ID":43,"did":"13_2"}
,{"status":["AOF","","OK",""],"name":"Trident_18_3","gid":"","type":"selector","ID":44,"did":"18_3"}
,{"status":["AOF","","OK",""],"name":"Alk_18_4","gid":"","type":"selector","ID":45,"did":"18_4"}
,{"status":["AOF","","OK",""],"name":"ATO_EMPTY","gid":"","type":"virtual","ID":46,"did":"Cntl_A16"}
,{"status":["OFF","","OK",""],"name":"TMP_DELETE","gid":"","type":"virtual","ID":47,"did":"Cntl_B1"}
,{"status":["TBL","","OK","2000","0"],"name":"AWC_REM","gid":"doserqd_3","type":"dqd","ID":48,"did":"3_2"}
,{"status":["AOF","","OK",""],"name":"LinkA_21_1","gid":"","type":"24v","ID":49,"did":"21_1"}
,{"status":["AOF","","OK",""],"name":"ATK_Lo_Alarm","gid":"","type":"virtual","ID":50,"did":"Cntl_A3"}
,{"status":["AOF","","OK",""],"name":"NSW_Pump","gid":"","type":"outlet","ID":51,"did":"2_3"}
,{"status":["AOF","","OK",""],"name":"RO_AUTOFILL","gid":"","type":"virtual","ID":52,"did":"Cntl_A4"}
,{"status":["TBL","","OK","2000","0"],"name":"QT_ADD","gid":"doserqd_23","type":"dqd","ID":53,"did":"23_1"}
,{"status":["TBL","","OK","2000","0"],"name":"QT_Remove","gid":"doserqd_23","type":"dqd","ID":54,"did":"23_2"}
,{"status":["AOF","","OK",""],"name":"Alarm_21_2","gid":"","type":"alert","ID":55,"did":"21_2"}
,{"status":["AOF","","OK",""],"name":"RES_BAD","gid":"","type":"virtual","ID":56,"did":"Cntl_B2"}
,{"status":["AOF","","OK",""],"name":"RO_Booster","gid":"","type":"outlet","ID":57,"did":"2_4"}
,{"status":["AON","","OK",""],"name":"Ozone","gid":"","type":"outlet","ID":58,"did":"2_5"}
,{"status":["AON","","OK",""],"name":"Pump_2_6","gid":"","type":"outlet","ID":59,"did":"2_6"}
,{"status":["AOF","","OK",""],"name":"Feeding","gid":"","type":"virtual","ID":60,"did":"Cntl_A5"}
,{"status":["AOF","","OK",""],"name":"SumpAlarm","gid":"","type":"virtual","ID":61,"did":"Cntl_A6"}
,{"status":["AON","","OK",""],"name":"Pulser","gid":"","type":"virtual","ID":62,"did":"Cntl_A7"}
,{"status":["OFF","","OK",""],"name":"NSW_AutoFill","gid":"","type":"virtual","ID":63,"did":"Cntl_A8"}
,{"status":["OFF","","OK",""],"name":"NSW_Trigger","gid":"","type":"virtual","ID":64,"did":"Cntl_A9"}
,{"status":["AOF","","OK",""],"name":"RefLght_2_7","gid":"","type":"outlet","ID":65,"did":"2_7"}
,{"status":["AOF","","OK",""],"name":"GPower8","gid":"","type":"outlet","ID":66,"did":"2_8"}
,{"status":["AOF","","OK",""],"name":"DDR_Low","gid":"","type":"virtual","ID":67,"did":"Cntl_A10"}
,{"status":["OFF","","OK",""],"name":"Mix_NSW","gid":"","type":"virtual","ID":68,"did":"Cntl_A11"}
,{"status":["AON","","OK",""],"name":"AWC_Enabled","gid":"","type":"virtual","ID":69,"did":"Cntl_A12"}
,{"status":["OFF","","OK",""],"name":"Alt_Fill","gid":"","type":"virtual","ID":70,"did":"Cntl_A13"}
,{"status":["OFF","","Werr",""],"name":"DT_ATO_PUMP","gid":"","type":"24v","ID":71,"did":"2_9"}
,{"status":["AOF","","OK",""],"name":"FRAG_ATO_PMP","gid":"","type":"24v","ID":72,"did":"2_10"}
,{"status":["OFF","","OK",""],"name":"TSM","gid":"","type":"virtual","ID":76,"did":"Cntl_A14"}
,{"status":["AOF","","OK",""],"name":"LinkA_22_1","gid":"","type":"24v","ID":77,"did":"22_1"}
,{"status":["AOF","","OK",""],"name":"Alarm_22_2","gid":"","type":"alert","ID":78,"did":"22_2"}
,{"status":["AOF","","OK",""],"name":"Trident_6_3","gid":"","type":"selector","ID":79,"did":"6_3"}
,{"status":["AOF","","OK",""],"name":"Skimmer_full","gid":"","type":"virtual","ID":80,"did":"Cntl_A15"}
,{"status":["AOF","","OK",""],"name":"SOL_INPUT","gid":"","type":"24v","ID":81,"did":"15_1"}
,{"status":["AOF","","OK",""],"name":"SOL_OUT_NSW","gid":"","type":"24v","ID":82,"did":"15_2"}
,{"status":["AOF","","OK",""],"name":"LinkA_14_1","gid":"","type":"24v","ID":83,"did":"14_1"}
,{"status":["AOF","","OK",""],"name":"Alarm_14_2","gid":"","type":"alert","ID":84,"did":"14_2"}
,{"status":["AOF","","OK",""],"name":"SOL_OUT_ATO","gid":"","type":"24v","ID":85,"did":"10_1"}
,{"status":["AOF","","OK",""],"name":"Alarm_10_2","gid":"","type":"alert","ID":86,"did":"10_2"}
,{"status":["AOF","0","OK","   0","0","73.9","0.04","-186","-239","977","0"],"intensity":0,"name":"Wav_Bottom","gid":"","type":"wav","ID":87,"did":"17_1"}
,{"status":["AOF","0","OK","   0","0","97.5","0.04","381","-565","-769","4"],"intensity":0,"name":"WAV_Top","gid":"","type":"wav","ID":88,"did":"16_1"}
],"link":{"linkState":3,"linkKey":"G9qXY7","link":false}}}
